pedhosp.py
pedhosp-0.0.3.dist-info/METADATA
pedhosp-0.0.3.dist-info/WHEEL
pedhosp-0.0.3.dist-info/entry_points.txt
pedhosp-0.0.3.dist-info/top_level.txt
pedhosp-0.0.3.dist-info/RECORD
