Metadata-Version: 2.1
Name: pedhosp
Version: 0.0.3
Summary: pediatric COVID-19 hospitalizations
Home-page: https://github.com/y-takefuji/pedhosp
Author: yoshiyasu takefuji
Author-email: takefuji@keio.jp
License: UNKNOWN
Project-URL: Bug Tracker, https://github.com/y-takefuji/pedhosp
Platform: UNKNOWN
Classifier: Programming Language :: Python :: 3
Classifier: License :: OSI Approved :: MIT License
Classifier: Operating System :: OS Independent
Requires-Python: >=3.8
